imagetileprocessor/__init__.py
imagetileprocessor/merge_peaks.py
imagetileprocessor/merge_polygons.py
imagetileprocessor/tile_2D_image.py
imagetileprocessor-0.1.16.dist-info/LICENSE
imagetileprocessor-0.1.16.dist-info/METADATA
imagetileprocessor-0.1.16.dist-info/WHEEL
imagetileprocessor-0.1.16.dist-info/entry_points.txt
imagetileprocessor-0.1.16.dist-info/RECORD
