Metadata-Version: 2.3
Name: ImageTileProcessor
Version: 0.1.16
Summary: This is a in-house package to deal with lazy tiled image tile loading to save RAM and various methods to post process tiled outpus s
License: MIT
Keywords: image,tiles,processing
Author: Tong Li
Author-email: tl10@sanger.ac.uk
Requires-Python: >=3.10,<4.0
Classifier: License :: OSI Approved :: MIT License
Classifier: Programming Language :: Python :: 3
Classifier: Programming Language :: Python :: 3.10
Classifier: Programming Language :: Python :: 3.11
Classifier: Programming Language :: Python :: 3.12
Classifier: Programming Language :: Python :: 3.13
Requires-Dist: aicsimageio[all] (>=4.12.1,<5.0.0)
Requires-Dist: bioformats-jar (>=2020.5.27,<2021.0.0)
Requires-Dist: fire (>=0.6.0,<0.7.0)
Requires-Dist: numpy (>=1.24.0,<2.0.0)
Requires-Dist: shapely (>=2.0.3,<3.0.0)
Requires-Dist: tifffile (>=2022.4.8,<2023.0.0)
Requires-Dist: tqdm (>=4.67.1,<5.0.0)
Project-URL: Homepage, https://github.com/BioinfoTongLI/ImageTileProcessor
Project-URL: Repository, https://github.com/BioinfoTongLI/ImageTileProcessor
